{
  "meta": {
    "version": "1.0",
    "model": "V4.4 (Logistic + Player EPM + B2B)",
    "created_at": "2025-11-30T14:00:49.732204+00:00",
    "game_date_et": "2025-10-26",
    "game_date_kst": "2025-10-27"
  },
  "summary": {
    "total_games": 9,
    "finished_games": 9,
    "correct_predictions": 7,
    "accuracy_pct": 77.8
  },
  "predictions": [
    {
      "game_id": "0022500105",
      "game_time": "2:00 pm ET",
      "home_team": "SAS",
      "away_team": "BKN",
      "home_b2b": false,
      "away_b2b": false,
      "home_win_prob": 79.8,
      "predicted_margin": 8.5,
      "predicted_winner": "SAS",
      "game_status": 3,
      "home_score": 118,
      "away_score": 107,
      "actual_winner": "SAS",
      "is_correct": true
    },
    {
      "game_id": "0022500106",
      "game_time": "3:30 pm ET",
      "home_team": "DET",
      "away_team": "BOS",
      "home_b2b": false,
      "away_b2b": false,
      "home_win_prob": 56.8,
      "predicted_margin": 2.1,
      "predicted_winner": "DET",
      "game_status": 3,
      "home_score": 119,
      "away_score": 113,
      "actual_winner": "DET",
      "is_correct": true
    },
    {
      "game_id": "0022500107",
      "game_time": "6:00 pm ET",
      "home_team": "CLE",
      "away_team": "MIL",
      "home_b2b": false,
      "away_b2b": false,
      "home_win_prob": 70.2,
      "predicted_margin": 6.4,
      "predicted_winner": "CLE",
      "game_status": 3,
      "home_score": 118,
      "away_score": 113,
      "actual_winner": "CLE",
      "is_correct": true
    },
    {
      "game_id": "0022500108",
      "game_time": "6:00 pm ET",
      "home_team": "MIA",
      "away_team": "NYK",
      "home_b2b": false,
      "away_b2b": false,
      "home_win_prob": 57.7,
      "predicted_margin": 2.3,
      "predicted_winner": "MIA",
      "game_status": 3,
      "home_score": 115,
      "away_score": 107,
      "actual_winner": "MIA",
      "is_correct": true
    },
    {
      "game_id": "0022500109",
      "game_time": "6:00 pm ET",
      "home_team": "WAS",
      "away_team": "CHA",
      "home_b2b": false,
      "away_b2b": true,
      "home_win_prob": 50.6,
      "predicted_margin": 0.2,
      "predicted_winner": "WAS",
      "game_status": 3,
      "home_score": 113,
      "away_score": 139,
      "actual_winner": "CHA",
      "is_correct": false
    },
    {
      "game_id": "0022500110",
      "game_time": "7:00 pm ET",
      "home_team": "MIN",
      "away_team": "IND",
      "home_b2b": false,
      "away_b2b": true,
      "home_win_prob": 87.2,
      "predicted_margin": 11.6,
      "predicted_winner": "MIN",
      "game_status": 3,
      "home_score": 114,
      "away_score": 110,
      "actual_winner": "MIN",
      "is_correct": true
    },
    {
      "game_id": "0022500111",
      "game_time": "7:30 pm ET",
      "home_team": "DAL",
      "away_team": "TOR",
      "home_b2b": false,
      "away_b2b": false,
      "home_win_prob": 28.8,
      "predicted_margin": -6.7,
      "predicted_winner": "TOR",
      "game_status": 3,
      "home_score": 139,
      "away_score": 129,
      "actual_winner": "DAL",
      "is_correct": false
    },
    {
      "game_id": "0022500112",
      "game_time": "9:00 pm ET",
      "home_team": "LAC",
      "away_team": "POR",
      "home_b2b": false,
      "away_b2b": false,
      "home_win_prob": 65.0,
      "predicted_margin": 4.6,
      "predicted_winner": "LAC",
      "game_status": 3,
      "home_score": 114,
      "away_score": 107,
      "actual_winner": "LAC",
      "is_correct": true
    },
    {
      "game_id": "0022500113",
      "game_time": "9:00 pm ET",
      "home_team": "SAC",
      "away_team": "LAL",
      "home_b2b": false,
      "away_b2b": false,
      "home_win_prob": 18.2,
      "predicted_margin": -9.2,
      "predicted_winner": "LAL",
      "game_status": 3,
      "home_score": 120,
      "away_score": 127,
      "actual_winner": "LAL",
      "is_correct": true
    }
  ],
  "integrity": {
    "hash_algorithm": "SHA256",
    "predictions_hash": "b753a284830364e8737de0ecd99306ec93d2ce4b154b76f26678448e817e2aa1"
  }
}